pyhc_core/__init__.py
pyhc_core-0.0.6.dist-info/LICENSE
pyhc_core-0.0.6.dist-info/METADATA
pyhc_core-0.0.6.dist-info/WHEEL
pyhc_core-0.0.6.dist-info/top_level.txt
pyhc_core-0.0.6.dist-info/RECORD
