Metadata-Version: 2.1
Name: pyhc-core
Version: 0.0.6
Summary: A package to install the core PyHC packages.
Author-email: Shawn Polson <pyhc-confidential@lasp.colorado.edu>
License: MIT License
Project-URL: Source, https://github.com/heliophysicsPy/pyhc-core
Classifier: Programming Language :: Python :: 3
Classifier: License :: OSI Approved :: MIT License
Classifier: Operating System :: OS Independent
License-File: LICENSE
Requires-Dist: hapiclient
Requires-Dist: kamodo
Requires-Dist: plasmapy
Requires-Dist: pysat
Requires-Dist: pyspedas
Requires-Dist: spacepy
Requires-Dist: sunpy[all]
Requires-Dist: numpy<2.0.0
Provides-Extra: tests
Requires-Dist: sunpy[tests]; extra == "tests"
Requires-Dist: plasmapy[tests]; extra == "tests"
Requires-Dist: pysat[test]; extra == "tests"
Requires-Dist: deepdiff; extra == "tests"
Requires-Dist: mth5; extra == "tests"
